code2doc/__init__.py
code2doc/__version__.py
code2doc/build_config.py
code2doc/builder.py
code2doc/configurer.py
code2doc/constants.py
code2doc/doc_types.py
code2doc/generator.py
code2doc/run.py
code2doc/utils.py
code2doc/renderer/__init__.py
code2doc/renderer/class_renderer.py
code2doc/renderer/function_renderer.py
code2doc/renderer/renderer.py
code2doc-0.0.4.dist-info/LICENSE
code2doc-0.0.4.dist-info/METADATA
code2doc-0.0.4.dist-info/WHEEL
code2doc-0.0.4.dist-info/entry_points.txt
code2doc-0.0.4.dist-info/top_level.txt
code2doc-0.0.4.dist-info/RECORD
