Metadata-Version: 2.1
Name: code2doc
Version: 0.0.4
Summary: A documentation utility for generating markdowns from docstring
Home-page: https://github.com/rahulsrma26/code2doc
Author: Rahul Sharma
Author-email: rahulsrma26@gmail.com
Maintainer: rahulsrma26
Maintainer-email: welcometors@gmail.com
License: LICENSE
Project-URL: Code, https://github.com/rahulsrma26/code2doc
Keywords: sharing streaming network setuptools development
Platform: any
Classifier: Programming Language :: Python :: 3
Classifier: Programming Language :: Python :: 3.6
Classifier: Programming Language :: Python :: 3.7
Classifier: Programming Language :: Python :: 3.8
Classifier: Programming Language :: Python :: 3.9
Classifier: Programming Language :: Python :: 3 :: Only
Classifier: License :: OSI Approved :: MIT License
Classifier: Operating System :: OS Independent
Classifier: Topic :: Documentation
Classifier: Topic :: Education
Classifier: Topic :: Software Development :: Documentation
Classifier: Topic :: Text Processing :: Markup :: Markdown
Classifier: Topic :: Software Development :: Libraries :: Python Modules
Classifier: Topic :: Utilities
Requires-Python: >= 3.6
